gllm_pipeline.cpython-312-x86_64-linux-gnu.so
gllm_pipeline.pyi
gllm_pipeline/__init__.pyi
gllm_pipeline/alias.pyi
gllm_pipeline/types.pyi
gllm_pipeline/exclusions/__init__.pyi
gllm_pipeline/exclusions/exclusion_manager.pyi
gllm_pipeline/exclusions/exclusion_set.pyi
gllm_pipeline/pipeline/__init__.pyi
gllm_pipeline/pipeline/pipeline.pyi
gllm_pipeline/pipeline/states.pyi
gllm_pipeline/pipeline/composer/__init__.pyi
gllm_pipeline/pipeline/composer/composer.pyi
gllm_pipeline/pipeline/composer/guard_composer.pyi
gllm_pipeline/pipeline/composer/if_else_composer.pyi
gllm_pipeline/pipeline/composer/parallel_composer.pyi
gllm_pipeline/pipeline/composer/switch_composer.pyi
gllm_pipeline/pipeline/composer/toggle_composer.pyi
gllm_pipeline/router/__init__.pyi
gllm_pipeline/router/lm_based_router.pyi
gllm_pipeline/router/router.pyi
gllm_pipeline/router/rule_based_router.pyi
gllm_pipeline/router/similarity_based_router.pyi
gllm_pipeline/router/utils.pyi
gllm_pipeline/router/aurelio_semantic_router/__init__.pyi
gllm_pipeline/router/aurelio_semantic_router/aurelio_semantic_router.pyi
gllm_pipeline/router/aurelio_semantic_router/bytes_compat_route.pyi
gllm_pipeline/router/aurelio_semantic_router/encoders/__init__.pyi
gllm_pipeline/router/aurelio_semantic_router/encoders/em_invoker_encoder.pyi
gllm_pipeline/router/aurelio_semantic_router/encoders/langchain_encoder.pyi
gllm_pipeline/router/aurelio_semantic_router/encoders/tei_encoder.pyi
gllm_pipeline/router/aurelio_semantic_router/index/__init__.pyi
gllm_pipeline/router/aurelio_semantic_router/index/aurelio_index.pyi
gllm_pipeline/router/aurelio_semantic_router/index/azure_ai_search_aurelio_index.pyi
gllm_pipeline/router/aurelio_semantic_router/index/vector_store_adapter_index.pyi
gllm_pipeline/router/preset/__init__.pyi
gllm_pipeline/router/preset/preset_loader.pyi
gllm_pipeline/router/preset/aurelio/__init__.pyi
gllm_pipeline/router/preset/aurelio/router_image_domain_specific.pyi
gllm_pipeline/router/preset/lm_based/__init__.pyi
gllm_pipeline_binary-0.4.32.dist-info/METADATA
gllm_pipeline_binary-0.4.32.dist-info/WHEEL
gllm_pipeline_binary-0.4.32.dist-info/top_level.txt
gllm_pipeline_binary-0.4.32.dist-info/RECORD
