Metadata-Version: 2.2
Name: gllm-pipeline-binary
Version: 0.4.32
Summary: A library containing components related to Gen AI applications pipeline orchestration.
Author-email: Dimitrij Ray <dimitrij.ray@gdplabs.id>, Henry Wicaksono <henry.wicaksono@gdplabs.id>, Kadek Denaya <kadek.d.r.diana@gdplabs.id>
Requires-Python: <3.13,>=3.11
Requires-Dist: pydantic<2.12.0,>=2.11.7
Requires-Dist: gllm-core-binary<0.4.0,>=0.3.0
Requires-Dist: gllm-inference-binary<0.6.0,>=0.5.0
Requires-Dist: aiohttp<3.14.0,>=3.13.3
Requires-Dist: langgraph<0.7.0,>=0.6.0
Requires-Dist: typing-extensions<5.0.0,>=4.5.0
Provides-Extra: dev
Requires-Dist: coverage<7.5.0,>=7.4.4; extra == "dev"
Requires-Dist: mypy<1.16.0,>=1.15.0; extra == "dev"
Requires-Dist: pre-commit<3.8.0,>=3.7.0; extra == "dev"
Requires-Dist: pytest<8.2.0,>=8.1.1; extra == "dev"
Requires-Dist: pytest-asyncio<0.24.0,>=0.23.6; extra == "dev"
Requires-Dist: pytest-cov<5.1.0,>=5.0.0; extra == "dev"
Requires-Dist: ruff<0.7.0,>=0.6.7; extra == "dev"
Provides-Extra: cache
Requires-Dist: gllm-datastore-binary[chroma]<0.6.0,>=0.5.0; extra == "cache"
Provides-Extra: multimodal-router
Requires-Dist: gllm-inference-binary[google]<0.6.0,>=0.5.0; extra == "multimodal-router"
Provides-Extra: semantic-router
Requires-Dist: azure-search-documents<12.0.0,>=11.5.1; extra == "semantic-router"
Requires-Dist: semantic-router<0.2.0,>=0.1.0; extra == "semantic-router"
